equidistantpoints/__init__.py
equidistantpoints/cli.py
equidistantpoints/coord_utils.py
equidistantpoints/edpoints.py
equidistantpoints-0.4.dist-info/METADATA
equidistantpoints-0.4.dist-info/RECORD
equidistantpoints-0.4.dist-info/WHEEL
equidistantpoints-0.4.dist-info/entry_points.txt
equidistantpoints-0.4.dist-info/top_level.txt
