Metadata-Version: 2.1
Name: equidistantpoints
Version: 0.4
Summary: Generates (almost) evenly distributed, equidistant points across a perfect sphere or the globe (in cartesian, ECEF and geodetic format)
Home-page: https://github.com/ksbg/equidistantpoints
Author: Kevin Baumgarten
Author-email: kevin@ksbg.io
License: UNKNOWN
Download-URL: https://github.com/ksbg/equidistantpoints/archive/0.2.tar.gz
Keywords: mathematics,geography,coordinates,equidistant,sphere,globe,earth
Platform: UNKNOWN
Classifier: Development Status :: 4 - Beta
Classifier: Intended Audience :: Science/Research
Classifier: Topic :: Scientific/Engineering :: Mathematics
Classifier: License :: OSI Approved :: MIT License
Classifier: Operating System :: OS Independent
Classifier: Programming Language :: Python :: 2.7
Classifier: Programming Language :: Python :: 3.4
Classifier: Programming Language :: Python :: 3.5
Classifier: Programming Language :: Python :: 3.6
Requires-Python: >=2.7, !=3.0.*, !=3.1.*, !=3.2.*, !=3.3.*, <4
